wxc/__init__.py
wxc/__main__.py
wxc/api.py
wxc/cli.py
wxc-7.2.0.dist-info/entry_points.txt
wxc-7.2.0.dist-info/licenses/LICENSE
wxc-7.2.0.dist-info/WHEEL
wxc-7.2.0.dist-info/METADATA
wxc-7.2.0.dist-info/RECORD
