Metadata-Version: 2.4
Name: wxc
Version: 7.2.0
Summary: A CLI facility to inspect Python environments.
Author: C.M.T. Robert
Requires-Python: >=3.10
Classifier: Development Status :: 5 - Production/Stable
Classifier: Environment :: Console
Classifier: Intended Audience :: Developers
Classifier: License :: OSI Approved :: GNU General Public License v3 (GPLv3)
Classifier: Programming Language :: Python :: 3
License-File: LICENSE
Requires-Dist: rich>=10.13.0
Project-URL: Changelog, https://github.com/neutrinoceros/wxc/blob/main/CHANGELOG.md
Project-URL: Homepage, https://github.com/neutrinoceros/wxc
